finalizer/__init__.py
finalizer/examples/example1.py
finalizer/examples/multi_process.py
finalizer/examples/multithread.py
finalizer/finalizer.py
finalizer-1.0.0.dist-info/LICENSE
finalizer-1.0.0.dist-info/METADATA
finalizer-1.0.0.dist-info/WHEEL
finalizer-1.0.0.dist-info/RECORD
