Metadata-Version: 2.1
Name: finalizer
Version: 1.0.0
Summary: This is a context manager to cleanup your environment. Your claenup code will be called even if the program is stopped by Ctrl-C or kill command.
Home-page: https://github.com/hirachan
License: MIT
Author: HIRANO Yoshitaka
Author-email: yo@hirano.cc
Requires-Python: >=3.8,<4.0
Classifier: License :: OSI Approved :: MIT License
Classifier: Programming Language :: Python :: 3
Classifier: Programming Language :: Python :: 3.8
Classifier: Programming Language :: Python :: 3.9
Classifier: Programming Language :: Python :: 3.10
Classifier: Programming Language :: Python :: 3.11
Project-URL: Repository, https://github.com/hirachan/finalizer
